kynaylibs/__init__.py
kynaylibs/version.py
kynaylibs/nan/__init__.py
kynaylibs/nan/utils/PyroHelpers.py
kynaylibs/nan/utils/__init__.py
kynaylibs/nan/utils/adminHelpers.py
kynaylibs/nan/utils/ai.py
kynaylibs/nan/utils/aiohttp_helper.py
kynaylibs/nan/utils/basic.py
kynaylibs/nan/utils/constants.py
kynaylibs/nan/utils/function.py
kynaylibs/nan/utils/inline.py
kynaylibs/nan/utils/interval.py
kynaylibs/nan/utils/misc.py
kynaylibs/nan/utils/parser.py
kynaylibs/nan/utils/pilter.py
kynaylibs/nan/utils/tools.py
kynaylibs/nan/utils/unpack.py
kynaylibs/nan/utils/utility.py
kynaylibs/nan/utils/db/__init__.py
kynaylibs/nan/utils/db/permit.py
kynaylibs-7.1.4.dist-info/LICENSE
kynaylibs-7.1.4.dist-info/METADATA
kynaylibs-7.1.4.dist-info/WHEEL
kynaylibs-7.1.4.dist-info/top_level.txt
kynaylibs-7.1.4.dist-info/RECORD
