Metadata-Version: 2.1
Name: kynaylibs
Version: 7.1.4
Summary: A Secure and Powerful Python-Pyrogram Based Library For Naya-Pyro.
Home-page: https://github.com/naya1503/kynaylibs
Author: naya1503
Author-email: cosmospanas70@gmail.com
License: GNU AFFERO GENERAL PUBLIC LICENSE (v3)
Project-URL: Bug Tracker, https://github.com/naya1503/kynaylibs/issues
Project-URL: Documentation, https://t.me/kynansupport
Project-URL: Source Code, https://github.com/naya1503/kynaylibs
Platform: UNKNOWN
Classifier: Programming Language :: Python :: 3
Classifier: Programming Language :: Python :: 3.8
Classifier: Programming Language :: Python :: 3.9
Classifier: Programming Language :: Python :: 3.10
Classifier: License :: OSI Approved :: GNU General Public License v3 (GPLv3)
Classifier: Operating System :: OS Independent
Requires-Python: >3.7, <3.11
License-File: LICENSE
Requires-Dist: Pillow
Requires-Dist: aiofiles (==22.1.0)
Requires-Dist: aiohttp
Requires-Dist: aiosqlite (<0.18.0,>=0.16.0)
Requires-Dist: dnspython
Requires-Dist: ffmpeg-python
Requires-Dist: flask
Requires-Dist: gunicorn
Requires-Dist: lottie
Requires-Dist: motor (==3.0.0)
Requires-Dist: openai
Requires-Dist: pyaes (==1.6.1)
Requires-Dist: pykeyboard
Requires-Dist: pymongo
Requires-Dist: pyrogram
Requires-Dist: pyromod (==1.1.0)
Requires-Dist: pysocks (==1.7.1)
Requires-Dist: python-dotenv
Requires-Dist: requests
Requires-Dist: textblob
Requires-Dist: tgcrypto
Requires-Dist: tracemoepy
Requires-Dist: urllib3
Requires-Dist: uvloop
Requires-Dist: wget
